[
  {
    "description": "    As a user\n    I want to be able to registration failed and clinic name file is required",
    "elements": [
      {
        "id": "regis;regis-on-digiclinic-failed-and-clinic-name-file-is-required",
        "keyword": "Scenario",
        "line": 6,
        "name": "Regis on digiclinic failed and clinic name file is required",
        "steps": [
          {
            "arguments": [],
            "keyword": "Given ",
            "name": "user browse digiclinic apps",
            "result": {
              "status": "passed",
              "duration": 3573900
            },
            "line": 7,
            "match": {
              "location": "Testing\\Functional-Testing-Pro3\\step-definitions\\regis-fail-clinic-steps.js:2"
            }
          },
          {
            "arguments": [],
            "keyword": "And ",
            "name": "user click regis menu to regis on digicilinic apps",
            "result": {
              "status": "passed",
              "duration": 1981000
            },
            "line": 8,
            "match": {
              "location": "Testing\\Functional-Testing-Pro3\\step-definitions\\regis-fail-clinic-steps.js:6"
            }
          },
          {
            "arguments": [],
            "keyword": "And ",
            "name": "user click submenu regis to regis on digicilinic apps",
            "result": {
              "status": "passed",
              "duration": 553000
            },
            "line": 9,
            "match": {
              "location": "Testing\\Functional-Testing-Pro3\\step-definitions\\regis-fail-clinic-steps.js:13"
            }
          },
          {
            "arguments": [],
            "keyword": "And ",
            "name": "user fill fullname to regis on digicilinic apps",
            "result": {
              "status": "passed",
              "duration": 377300
            },
            "line": 10,
            "match": {
              "location": "Testing\\Functional-Testing-Pro3\\step-definitions\\regis-fail-clinic-steps.js:20"
            }
          },
          {
            "arguments": [],
            "keyword": "And ",
            "name": "user fill email to regis on digicilinic apps",
            "result": {
              "status": "passed",
              "duration": 957400
            },
            "line": 11,
            "match": {
              "location": "Testing\\Functional-Testing-Pro3\\step-definitions\\regis-fail-clinic-steps.js:26"
            }
          },
          {
            "arguments": [],
            "keyword": "And ",
            "name": "user fill phone number to regis on digicilinic apps",
            "result": {
              "status": "passed",
              "duration": 1413400
            },
            "line": 12,
            "match": {
              "location": "Testing\\Functional-Testing-Pro3\\step-definitions\\regis-fail-clinic-steps.js:32"
            }
          },
          {
            "arguments": [],
            "keyword": "And ",
            "name": "user fill clinic name field to regis on digicilinic apps",
            "result": {
              "status": "passed",
              "duration": 635000
            },
            "line": 13,
            "match": {
              "location": "Testing\\Functional-Testing-Pro3\\step-definitions\\regis-fail-clinic-steps.js:38"
            }
          },
          {
            "arguments": [],
            "keyword": "When ",
            "name": "user click regis button to regis on digicilinic apps",
            "result": {
              "status": "passed",
              "duration": 2891300
            },
            "line": 14,
            "match": {
              "location": "Testing\\Functional-Testing-Pro3\\step-definitions\\regis-fail-clinic-steps.js:44"
            }
          },
          {
            "arguments": [],
            "keyword": "Then ",
            "name": "the user failed regis and the clinic field is required",
            "result": {
              "status": "passed",
              "duration": 1067000
            },
            "line": 15,
            "match": {
              "location": "Testing\\Functional-Testing-Pro3\\step-definitions\\regis-fail-clinic-steps.js:50"
            }
          },
          {
            "arguments": [],
            "keyword": "After ",
            "result": {
              "status": "passed",
              "duration": 18243622400
            },
            "hidden": true,
            "match": {
              "location": "Testing\\Functional-Testing-Pro3\\node_modules\\selenium-cucumber-js\\runtime\\world.js:250"
            }
          }
        ],
        "tags": [],
        "type": "scenario"
      }
    ],
    "id": "regis",
    "keyword": "Feature",
    "line": 2,
    "name": "Regis",
    "tags": [],
    "uri": "D:\\Automation Testing\\Functional-Testing-Pro3\\features\\regis-fail-clinic.feature"
  }
]